langchain_standard_tests/__init__.py
langchain_standard_tests/integration_tests/__init__.py
langchain_standard_tests/integration_tests/base_store.py
langchain_standard_tests/integration_tests/cache.py
langchain_standard_tests/integration_tests/chat_models.py
langchain_standard_tests/integration_tests/vectorstores.py
langchain_standard_tests/py.typed
langchain_standard_tests/unit_tests/__init__.py
langchain_standard_tests/unit_tests/chat_models.py
gigachain_standard_tests-0.1.1.dist-info/METADATA
gigachain_standard_tests-0.1.1.dist-info/WHEEL
gigachain_standard_tests-0.1.1.dist-info/RECORD
