Metadata-Version: 2.1
Name: gigachain-standard-tests
Version: 0.1.1
Summary: Standard tests for GigaChain implementations
Home-page: https://github.com/ai-forever/gigachain
License: MIT
Author: Erick Friis
Author-email: erick@langchain.dev
Requires-Python: >=3.8.1,<4.0
Classifier: License :: OSI Approved :: MIT License
Classifier: Programming Language :: Python :: 3
Classifier: Programming Language :: Python :: 3.9
Classifier: Programming Language :: Python :: 3.10
Classifier: Programming Language :: Python :: 3.11
Classifier: Programming Language :: Python :: 3.12
Requires-Dist: gigachain-core (>=0.1.40,<0.3)
Requires-Dist: httpx (>=0.27.0,<0.28.0)
Requires-Dist: pytest (>=7,<9)
Project-URL: Repository, https://github.com/ai-forever/gigachain
Project-URL: Source Code, https://github.com/ai-forever/gigachain/tree/master/libs/standard-tests
